pulpfiction/__init__.py
pulpfiction/cli.py
pulpfiction/exceptions.py
pulpfiction/models.py
pulpfiction/parser.py
pulpfiction/service.py
pulpfiction/validator.py
pulpfiction-0.3.0.dist-info/DESCRIPTION.rst
pulpfiction-0.3.0.dist-info/METADATA
pulpfiction-0.3.0.dist-info/RECORD
pulpfiction-0.3.0.dist-info/WHEEL
pulpfiction-0.3.0.dist-info/entry_points.txt
pulpfiction-0.3.0.dist-info/metadata.json
pulpfiction-0.3.0.dist-info/top_level.txt
tinyfn/__init__.py
tinyfn/cli.py
tinyfn/exceptions.py
tinyfn/models.py
tinyfn/parser.py
tinyfn/service.py
tinyfn/validator.py
