Metadata-Version: 2.0
Name: pulpfiction
Version: 0.3.0
Summary: A simple utility tool to detect non-English comments in code
Home-page: https://github.com/kelvintaywl/pulpfiction
Author: Kelvin Tay
Author-email: kelvintaywl@gmail.com
License: UNKNOWN
Platform: any
Classifier: Intended Audience :: Developers
Classifier: Programming Language :: Python
Classifier: Programming Language :: Python :: 3
Classifier: Programming Language :: Python :: 3.4
Classifier: Programming Language :: Python :: 3.5
Classifier: Programming Language :: Python :: 3.6
Requires-Dist: pygments (>=2.2.0)
Requires-Dist: langdetect (>=1.0.7)
Requires-Dist: click (>=6.7)
Provides-Extra: dev
Requires-Dist: flake8 (>=3.5.0); extra == 'dev'
